r2d3shift/__init__.py
r2d3shift/__main__.py
r2d3shift/cli.py
r2d3shift/io.py
r2d3shift/noise.py
r2d3shift/peaks.py
r2d3shift/peaks_core.py
r2d3shift/plot.py
r2d3shift/shift.py
r2d3shift/signal.py
r2d3shift/simulation.py
r2d3shift/validation.py
r2d3shift/version.py
r2d3shift-1.617978.dist-info/LICENSE
r2d3shift-1.617978.dist-info/METADATA
r2d3shift-1.617978.dist-info/WHEEL
r2d3shift-1.617978.dist-info/RECORD
