Metadata-Version: 2.3
Name: r2d3shift
Version: 1.617978
Summary: Fix the misalignments of spectra from R2D3 sequence due to varying thermal conditions.
License: CECILL-2.1
Author: Julien PONTABRY
Author-email: jpontabry@unistra.fr
Requires-Python: >=3.12
Classifier: License :: OSI Approved :: CEA CNRS Inria Logiciel Libre License, version 2.1 (CeCILL-2.1)
Classifier: Programming Language :: Python :: 3
Classifier: Programming Language :: Python :: 3.12
Classifier: Programming Language :: Python :: 3.13
Provides-Extra: cli
Requires-Dist: click (>=8.2.1,<9.0.0) ; extra == "cli"
Requires-Dist: matplotlib (>=3.10.3,<4.0.0) ; extra == "cli"
Requires-Dist: numpy (>=2.3.1,<3.0.0)
Requires-Dist: pandas (>=2.3.1,<3.0.0) ; extra == "cli"
Requires-Dist: rich (>=14.1.0,<15.0.0) ; extra == "cli"
Requires-Dist: rich-click (>=1.8.9,<2.0.0) ; extra == "cli"
Requires-Dist: scipy (>=1.16.1,<2.0.0)
Requires-Dist: seaborn (>=0.13.2,<0.14.0) ; extra == "cli"
